{
  "schema": "devcap1.schema.json",
  "uuid": "eb70937d-16de-48f6-9aef-e50a6c0831f6",
  "manufacturername": [
    " _TZ3000_itb0omhv",
    "_TZ3000_4upl1fcj",
    "_TZ3000_wqcbzbae",
    "_TZ3000_tk3s5tyg",
    "_TZ3000_mrpevh8p",
    "_TZ3000_qgwcxxws",
    "_TZ3000_yj6k7vfo",
    "_TZ3000_axpdxqgu"
  ],
  "modelid": [
    "TS0041",
    "TS0041",
    "TS0041",
    "TS0041",
    "TS0041",
    "TS0041",
    "TS0041",
    "TS0041"
  ],
  "vendor": "Tuya",
  "product": "1-gang remote (TS0041)",
  "sleeper": false,
  "status": "Gold",
  "subdevices": [
    {
      "type": "$TYPE_SWITCH",
      "restapi": "/sensors",
      "uuid": [
        "$address.ext",
        "0x01",
        "0x0006"
      ],
      "items": [
        {
          "name": "attr/id"
        },
        {
          "name": "attr/lastannounced"
        },
        {
          "name": "attr/lastseen"
        },
        {
          "name": "attr/manufacturername"
        },
        {
          "name": "attr/modelid"
        },
        {
          "name": "attr/name"
        },
        {
          "name": "attr/swversion",
          "parse": {
            "fn": "zcl:attr",
            "ep": 1,
            "cl": "0x0000",
            "at": "0x0001",
            "script": "tuya_swversion.js"
          },
          "read": {
            "fn": "zcl:attr",
            "ep": 1,
            "cl": "0x0000",
            "at": "0x0001"
          }
        },
        {
          "name": "attr/type"
        },
        {
          "name": "attr/uniqueid"
        },
        {
          "name": "config/battery",
          "awake": true,
          "read": {
            "at": "0x0021",
            "cl": "0x0001",
            "ep": 1,
            "fn": "zcl:attr"
          },
          "parse": {
            "at": "0x0021",
            "cl": "0x0001",
            "ep": 1,
            "eval": "Item.val = Attr.val / 2"
          },
          "default": 0
        },
        {
          "name": "config/on"
        },
        {
          "name": "config/reachable"
        },
        {
          "name": "state/buttonevent"
        },
        {
          "name": "state/lastupdated"
        }
      ]
    }
  ],
  "bindings": [
    {
      "bind": "unicast",
      "src.ep": 1,
      "cl": "0x0001",
      "report": [
        {
          "at": "0x0021",
          "dt": "0x20",
          "min": 60,
          "max": 3600,
          "change": "0x00000001"
        }
      ]
    },
    {
      "bind": "unicast",
      "src.ep": 1,
      "dst.ep": 1,
      "cl": "0x0006"
    }
  ]
}
